{
  "Version": 3,
  "Meta": {
    "Duration": 2.367,
    "Fps": 30.0,
    "Loop": true,
    "AreBeziersRestricted": true,
    "CurveCount": 240,
    "TotalSegmentCount": 595,
    "TotalPointCount": 1237,
    "UserDataCount": 1,
    "TotalUserDataSize": 0
  },
  "Curves": [
    {
      "Target": "Parameter",
      "Id": "ParamAngleX",
      "Segments": [
        0,
        0,
        1,
        0.222,
        1.547,
        0.445,
        3,
        0.667,
        3,
        0,
        1.667,
        -12,
        1,
        1.9,
        -12,
        2.134,
        -6.258,
        2.367,
        -0.78
      ]
    },
    {
      "Target": "Parameter",
      "Id": "ParamAngleY",
      "Segments": [
        0,
        0,
        1,
        0.222,
        -6.809,
        0.445,
        -14,
        0.667,
        -14,
        0,
        1.667,
        18,
        1,
        1.9,
        18,
        2.134,
        9.555,
        2.367,
        1.193
      ]
    },
    {
      "Target": "Parameter",
      "Id": "ParamAngleZ",
      "Segments": [
        0,
        7,
        0,
        1.2,
        21,
        1,
        1.589,
        21,
        1.978,
        7.767,
        2.367,
        7.032
      ]
    },
    {
      "Target": "Parameter",
      "Id": "ParamEyeLOpen",
      "Segments": [
        0,
        1,
        2,
        1.833,
        1,
        0,
        2,
        0,
        0,
        2.267,
        1,
        2,
        2.367,
        1
      ]
    },
    {
      "Target": "Parameter",
      "Id": "ParamEyeROpen",
      "Segments": [
        0,
        1,
        2,
        1.833,
        1,
        0,
        2,
        0,
        0,
        2.267,
        1,
        2,
        2.367,
        1
      ]
    },
    {
      "Target": "Parameter",
      "Id": "ParamBodyAngleX",
      "Segments": [
        0,
        5,
        0,
        1.2,
        -4,
        0,
        2.367,
        5
      ]
    },
    {
      "Target": "Parameter",
      "Id": "Paramxiashen",
      "Segments": [
        0,
        -21.486,
        1,
        0.267,
        -0.221,
        0.533,
        16.776,
        0.8,
        25.72,
        1,
        0.889,
        29.184,
        0.978,
        30,
        1.067,
        30,
        0,
        2.267,
        -24,
        1,
        2.3,
        -24,
        2.334,
        -23.641,
        2.367,
        -22.67
      ]
    },
    {
      "Target": "Parameter",
      "Id": "ParamBodyAngleY",
      "Segments": [
        0,
        -7,
        0,
        1.2,
        10,
        1,
        1.589,
        10,
        1.978,
        -6.069,
        2.367,
        -6.961
      ]
    },
    {
      "Target": "Parameter",
      "Id": "ParamBodyAngleZ",
      "Segments": [
        0,
        0,
        0,
        1.2,
        -9,
        1,
        1.589,
        -9,
        1.978,
        -0.493,
        2.367,
        -0.02
      ]
    },
    {
      "Target": "Parameter",
      "Id": "Param58",
      "Segments": [
        0,
        1,
        0,
        1.2,
        0,
        1,
        1.589,
        0,
        1.978,
        0.945,
        2.367,
        0.998
      ]
    },
    {
      "Target": "Parameter",
      "Id": "Param",
      "Segments": [
        0,
        0,
        1,
        0.2,
        -3.574,
        0.4,
        -7,
        0.6,
        -7,
        0,
        1.8,
        30,
        1,
        1.989,
        30,
        2.178,
        15.908,
        2.367,
        2.379
      ]
    },
    {
      "Target": "Parameter",
      "Id": "Param31",
      "Segments": [
        0,
        -7.281,
        1,
        0.3,
        9.824,
        0.6,
        29,
        0.9,
        29,
        0,
        2.1,
        -14,
        1,
        2.189,
        -14,
        2.278,
        -13.935,
        2.367,
        -9.259
      ]
    },
    {
      "Target": "Parameter",
      "Id": "Param32",
      "Segments": [
        0,
        -0.156,
        1,
        0.3,
        -0.552,
        0.6,
        -1,
        0.9,
        -1,
        0,
        2.1,
        0,
        1,
        2.189,
        0,
        2.278,
        0,
        2.367,
        -0.11
      ]
    },
    {
      "Target": "Parameter",
      "Id": "Param59",
      "Segments": [
        0,
        0,
        1,
        0.2,
        7.866,
        0.4,
        16,
        0.6,
        16,
        0,
        1.8,
        -9,
        1,
        1.989,
        -9,
        2.178,
        -5.048,
        2.367,
        -0.76
      ]
    },
    {
      "Target": "Parameter",
      "Id": "Param60",
      "Segments": [
        0,
        0,
        1,
        0.2,
        0,
        0.4,
        -1.184,
        0.6,
        -8,
        1,
        0.744,
        -12.923,
        0.889,
        -21,
        1.033,
        -21,
        1,
        1.289,
        -21,
        1.544,
        -7.387,
        1.8,
        -3,
        1,
        1.989,
        0.242,
        2.178,
        0.036,
        2.367,
        0.003
      ]
    },
    {
      "Target": "Parameter",
      "Id": "Param61",
      "Segments": [
        0,
        0,
        1,
        0.2,
        3.697,
        0.4,
        7,
        0.6,
        7,
        0,
        1.8,
        -17,
        1,
        1.989,
        -17,
        2.178,
        -9.159,
        2.367,
        -1.372
      ]
    },
    {
      "Target": "Parameter",
      "Id": "Param62",
      "Segments": [
        0,
        0,
        2,
        0.267,
        0,
        1,
        0.456,
        0,
        0.644,
        1.997,
        0.833,
        2,
        1,
        0.955,
        2,
        1.078,
        0.473,
        1.2,
        0.309,
        1,
        1.422,
        0.097,
        1.645,
        0.026,
        1.867,
        0,
        2,
        2.367,
        0
      ]
    },
    {
      "Target": "Parameter",
      "Id": "Param36",
      "Segments": [
        0,
        -4,
        0,
        0.767,
        1,
        0,
        1.567,
        -12,
        1,
        1.834,
        -12,
        2.1,
        -4.627,
        2.367,
        -4.037
      ]
    },
    {
      "Target": "Parameter",
      "Id": "Param35",
      "Segments": [
        0,
        20,
        0,
        0.767,
        0,
        1,
        1.034,
        0,
        1.3,
        -0.259,
        1.567,
        1,
        1,
        1.834,
        2.259,
        2.1,
        18.611,
        2.367,
        19.917
      ]
    },
    {
      "Target": "Parameter",
      "Id": "Param34",
      "Segments": [
        0,
        1.042,
        0,
        0.167,
        0,
        1,
        0.422,
        0,
        0.678,
        0.847,
        0.933,
        4,
        1,
        1.2,
        7.29,
        1.466,
        10,
        1.733,
        10,
        1,
        1.944,
        10,
        2.156,
        6.25,
        2.367,
        1.757
      ]
    },
    {
      "Target": "Parameter",
      "Id": "Param33",
      "Segments": [
        0,
        -1.146,
        0,
        0.167,
        0,
        1,
        0.422,
        0,
        0.678,
        0.212,
        0.933,
        -1,
        1,
        1.2,
        -2.265,
        1.466,
        -11,
        1.733,
        -11,
        1,
        1.944,
        -11,
        2.156,
        -6.869,
        2.367,
        -1.932
      ]
    },
    {
      "Target": "Parameter",
      "Id": "Param38",
      "Segments": [
        0,
        -5,
        0,
        0.767,
        28,
        1,
        1.034,
        28,
        1.3,
        13.739,
        1.567,
        5,
        1,
        1.834,
        -3.739,
        2.1,
        -4.915,
        2.367,
        -4.995
      ]
    },
    {
      "Target": "Parameter",
      "Id": "Param37",
      "Segments": [
        0,
        16,
        1,
        0.256,
        16,
        0.511,
        2.654,
        0.767,
        -10,
        1,
        1.034,
        -23.204,
        1.3,
        -26,
        1.567,
        -26,
        1,
        1.834,
        -26,
        2.1,
        12.707,
        2.367,
        15.804
      ]
    },
    {
      "Target": "Parameter",
      "Id": "Param40",
      "Segments": [
        0,
        0,
        0,
        0.567,
        -15,
        1,
        0.945,
        -15,
        1.322,
        -12.997,
        1.7,
        -7,
        1,
        1.922,
        -3.473,
        2.145,
        -0.315,
        2.367,
        -0.022
      ]
    },
    {
      "Target": "Parameter",
      "Id": "Param39",
      "Segments": [
        0,
        0,
        0,
        0.567,
        -19,
        0,
        1.7,
        30,
        1,
        1.922,
        30,
        2.145,
        2.789,
        2.367,
        0.198
      ]
    },
    {
      "Target": "Parameter",
      "Id": "Param_Angle_Rotation4",
      "Segments": [
        0,
        0,
        0,
        1.2,
        4,
        1,
        1.589,
        4,
        1.978,
        0.219,
        2.367,
        0.009
      ]
    },
    {
      "Target": "Parameter",
      "Id": "Param_Angle_Rotation5",
      "Segments": [
        0,
        0,
        0,
        1.2,
        -17,
        1,
        1.589,
        -17,
        1.978,
        -0.931,
        2.367,
        -0.039
      ]
    },
    {
      "Target": "Parameter",
      "Id": "Param_Angle_Rotation6",
      "Segments": [
        0,
        0,
        0,
        1.2,
        10,
        1,
        1.589,
        10,
        1.978,
        0.548,
        2.367,
        0.023
      ]
    },
    {
      "Target": "Parameter",
      "Id": "Param_Angle_Rotation7",
      "Segments": [
        0,
        0,
        0,
        1.2,
        -12,
        1,
        1.589,
        -12,
        1.978,
        -0.657,
        2.367,
        -0.027
      ]
    },
    {
      "Target": "Parameter",
      "Id": "Param_Angle_Rotation8",
      "Segments": [
        0,
        0,
        0,
        1.2,
        -3,
        1,
        1.589,
        -3,
        1.978,
        -0.164,
        2.367,
        -0.007
      ]
    },
    {
      "Target": "Parameter",
      "Id": "Param_Angle_Rotation9",
      "Segments": [
        0,
        0,
        0,
        1.2,
        13,
        1,
        1.589,
        13,
        1.978,
        0.712,
        2.367,
        0.03
      ]
    },
    {
      "Target": "Parameter",
      "Id": "Param_Angle_Rotation10",
      "Segments": [
        0,
        0,
        0,
        1.2,
        2,
        1,
        1.589,
        2,
        1.978,
        0.11,
        2.367,
        0.005
      ]
    },
    {
      "Target": "Parameter",
      "Id": "Param_Angle_Rotation11",
      "Segments": [
        0,
        0,
        0,
        1.2,
        10,
        1,
        1.589,
        10,
        1.978,
        0.548,
        2.367,
        0.023
      ]
    },
    {
      "Target": "Parameter",
      "Id": "Param_Angle_Rotation27",
      "Segments": [
        0,
        0,
        0,
        1.2,
        8,
        1,
        1.589,
        8,
        1.978,
        0.438,
        2.367,
        0.018
      ]
    },
    {
      "Target": "Parameter",
      "Id": "Param_Angle_Rotation28",
      "Segments": [
        0,
        0,
        0,
        1.2,
        13,
        1,
        1.589,
        13,
        1.978,
        0.712,
        2.367,
        0.03
      ]
    },
    {
      "Target": "Parameter",
      "Id": "Param_Angle_Rotation29",
      "Segments": [
        0,
        0,
        0,
        1.2,
        12,
        1,
        1.589,
        12,
        1.978,
        0.657,
        2.367,
        0.027
      ]
    },
    {
      "Target": "Parameter",
      "Id": "Param_Angle_Rotation21",
      "Segments": [
        0,
        0,
        0,
        1.2,
        -5,
        1,
        1.589,
        -5,
        1.978,
        -0.274,
        2.367,
        -0.011
      ]
    },
    {
      "Target": "Parameter",
      "Id": "Param_Angle_Rotation23",
      "Segments": [
        0,
        0,
        0,
        1.2,
        9,
        1,
        1.589,
        9,
        1.978,
        0.493,
        2.367,
        0.02
      ]
    },
    {
      "Target": "Parameter",
      "Id": "Param_Angle_Rotation24",
      "Segments": [
        0,
        0,
        0,
        1.2,
        -6,
        1,
        1.589,
        -6,
        1.978,
        -0.329,
        2.367,
        -0.014
      ]
    },
    {
      "Target": "Parameter",
      "Id": "Param_Angle_Rotation26",
      "Segments": [
        0,
        0,
        0,
        1.2,
        5,
        1,
        1.589,
        5,
        1.978,
        0.274,
        2.367,
        0.011
      ]
    },
    {
      "Target": "Parameter",
      "Id": "Param_Angle_Rotation30",
      "Segments": [
        0,
        0,
        0,
        1.2,
        -4,
        1,
        1.589,
        -4,
        1.978,
        -0.219,
        2.367,
        -0.009
      ]
    },
    {
      "Target": "Parameter",
      "Id": "Param_Angle_Rotation31",
      "Segments": [
        0,
        0,
        0,
        1.2,
        -9,
        1,
        1.589,
        -9,
        1.978,
        -0.493,
        2.367,
        -0.02
      ]
    },
    {
      "Target": "Parameter",
      "Id": "Param_Angle_Rotation18",
      "Segments": [
        0,
        0,
        0,
        1.2,
        -9,
        1,
        1.589,
        -9,
        1.978,
        -0.493,
        2.367,
        -0.02
      ]
    },
    {
      "Target": "Parameter",
      "Id": "Param_Angle_Rotation19",
      "Segments": [
        0,
        0,
        0,
        1.2,
        4,
        1,
        1.589,
        4,
        1.978,
        0.219,
        2.367,
        0.009
      ]
    },
    {
      "Target": "Parameter",
      "Id": "Param_Angle_Rotation20",
      "Segments": [
        0,
        0,
        0,
        1.2,
        8,
        1,
        1.589,
        8,
        1.978,
        0.438,
        2.367,
        0.018
      ]
    },
    {
      "Target": "Parameter",
      "Id": "Param_Angle_Rotation70",
      "Segments": [
        0,
        -2,
        0,
        1.2,
        15,
        1,
        1.589,
        15,
        1.978,
        -1.069,
        2.367,
        -1.961
      ]
    },
    {
      "Target": "Parameter",
      "Id": "Param_Angle_Rotation71",
      "Segments": [
        0,
        -6.953,
        0,
        0.167,
        -8,
        0,
        1.367,
        12,
        1,
        1.7,
        12,
        2.034,
        3.374,
        2.367,
        -6.012
      ]
    },
    {
      "Target": "Parameter",
      "Id": "Param_Angle_Rotation72",
      "Segments": [
        0,
        -4.92,
        0,
        0.467,
        -16,
        0,
        1.667,
        17,
        1,
        1.9,
        17,
        2.134,
        9.099,
        2.367,
        -3.142
      ]
    },
    {
      "Target": "Parameter",
      "Id": "Param_Angle_Rotation77",
      "Segments": [
        0,
        -2,
        0,
        1.2,
        4,
        1,
        1.589,
        4,
        1.978,
        -1.671,
        2.367,
        -1.986
      ]
    },
    {
      "Target": "Parameter",
      "Id": "Param_Angle_Rotation78",
      "Segments": [
        0,
        -5.537,
        0,
        0.367,
        -10,
        0,
        1.567,
        10,
        1,
        1.834,
        10,
        2.1,
        3.845,
        2.367,
        -4.484
      ]
    },
    {
      "Target": "Parameter",
      "Id": "Param_Angle_Rotation79",
      "Segments": [
        0,
        -1.556,
        0,
        0.2,
        -2,
        0,
        1.4,
        4,
        1,
        1.722,
        4,
        2.045,
        1.566,
        2.367,
        -1.262
      ]
    },
    {
      "Target": "Parameter",
      "Id": "Param_Angle_Rotation80",
      "Segments": [
        0,
        2.541,
        0,
        0.567,
        -8,
        0,
        1.767,
        15,
        1,
        1.967,
        15,
        2.167,
        11.074,
        2.367,
        3.786
      ]
    },
    {
      "Target": "Parameter",
      "Id": "Param_Angle_Rotation81",
      "Segments": [
        0,
        -1.971,
        0,
        0.467,
        -6,
        0,
        1.667,
        6,
        1,
        1.9,
        6,
        2.134,
        3.131,
        2.367,
        -1.324
      ]
    },
    {
      "Target": "Parameter",
      "Id": "Param_Angle_Rotation82",
      "Segments": [
        0,
        10.81,
        0,
        0.8,
        -4,
        0,
        2,
        16,
        1,
        2.122,
        16,
        2.245,
        15.255,
        2.367,
        11.817
      ]
    },
    {
      "Target": "Parameter",
      "Id": "Param_Angle_Rotation83",
      "Segments": [
        0,
        0,
        0,
        1.2,
        7,
        1,
        1.589,
        7,
        1.978,
        0.383,
        2.367,
        0.016
      ]
    },
    {
      "Target": "Parameter",
      "Id": "Param_Angle_Rotation84",
      "Segments": [
        0,
        0,
        0,
        1.2,
        18,
        1,
        1.589,
        18,
        1.978,
        0.986,
        2.367,
        0.041
      ]
    },
    {
      "Target": "Parameter",
      "Id": "Param_Angle_Rotation85",
      "Segments": [
        0,
        -5.518,
        0,
        0.133,
        -6,
        0,
        1.333,
        8,
        1,
        1.678,
        8,
        2.022,
        1.811,
        2.367,
        -4.87
      ]
    },
    {
      "Target": "Parameter",
      "Id": "Param_Angle_Rotation86",
      "Segments": [
        0,
        -0.991,
        0,
        0.367,
        -3,
        0,
        1.567,
        6,
        1,
        1.834,
        6,
        2.1,
        3.243,
        2.367,
        -0.516
      ]
    },
    {
      "Target": "Parameter",
      "Id": "Param_Angle_Rotation87",
      "Segments": [
        0,
        9.366,
        0,
        0.7,
        -4,
        0,
        1.9,
        17,
        1,
        2.056,
        17,
        2.211,
        15.361,
        2.367,
        10.466
      ]
    },
    {
      "Target": "Parameter",
      "Id": "Param_Angle_Rotation88",
      "Segments": [
        0,
        20.528,
        0,
        0.867,
        -3,
        0,
        2.067,
        26,
        1,
        2.167,
        26,
        2.267,
        25.665,
        2.367,
        21.911
      ]
    },
    {
      "Target": "Parameter",
      "Id": "Param_Angle_Rotation89",
      "Segments": [
        0,
        0,
        0,
        1.2,
        1,
        1,
        1.589,
        1,
        1.978,
        0.055,
        2.367,
        0.002
      ]
    },
    {
      "Target": "Parameter",
      "Id": "Param_Angle_Rotation90",
      "Segments": [
        0,
        -6.69,
        0,
        0.133,
        -7,
        0,
        1.333,
        2,
        1,
        1.678,
        2,
        2.022,
        -1.941,
        2.367,
        -6.27
      ]
    },
    {
      "Target": "Parameter",
      "Id": "Param_Angle_Rotation91",
      "Segments": [
        0,
        -10.226,
        0,
        0.333,
        -14,
        0,
        1.533,
        6,
        1,
        1.811,
        6,
        2.089,
        -0.604,
        2.367,
        -9.187
      ]
    },
    {
      "Target": "Parameter",
      "Id": "Param_Angle_Rotation92",
      "Segments": [
        0,
        -1,
        0,
        0.6,
        -17,
        0,
        1.8,
        15,
        1,
        1.989,
        15,
        2.178,
        10.243,
        2.367,
        0.728
      ]
    },
    {
      "Target": "Parameter",
      "Id": "Param_Angle_Rotation93",
      "Segments": [
        0,
        -1,
        0,
        1.2,
        1,
        1,
        1.589,
        1,
        1.978,
        -0.89,
        2.367,
        -0.995
      ]
    },
    {
      "Target": "Parameter",
      "Id": "Param_Angle_Rotation94",
      "Segments": [
        0,
        -2.991,
        0,
        0.367,
        -5,
        0,
        1.567,
        4,
        1,
        1.834,
        4,
        2.1,
        1.243,
        2.367,
        -2.516
      ]
    },
    {
      "Target": "Parameter",
      "Id": "Param_Angle_Rotation95",
      "Segments": [
        0,
        -3.959,
        0,
        0.567,
        -9,
        0,
        1.767,
        2,
        1,
        1.967,
        2,
        2.167,
        0.123,
        2.367,
        -3.363
      ]
    },
    {
      "Target": "Parameter",
      "Id": "Param_Angle_Rotation96",
      "Segments": [
        0,
        16.72,
        0,
        0.933,
        -6,
        0,
        2.133,
        20,
        1,
        2.211,
        20,
        2.289,
        20.169,
        2.367,
        17.866
      ]
    },
    {
      "Target": "Parameter",
      "Id": "Param_Angle_Rotation97",
      "Segments": [
        0,
        -8.208,
        1,
        0.356,
        3.006,
        0.711,
        14,
        1.067,
        14,
        0,
        2.267,
        -9,
        1,
        2.3,
        -9,
        2.334,
        -9.343,
        2.367,
        -8.923
      ]
    },
    {
      "Target": "Parameter",
      "Id": "Param_Angle_Rotation98",
      "Segments": [
        0,
        -6,
        0,
        1.2,
        -3,
        1,
        1.589,
        -3,
        1.978,
        -5.836,
        2.367,
        -5.993
      ]
    },
    {
      "Target": "Parameter",
      "Id": "Param_Angle_Rotation99",
      "Segments": [
        0,
        -14.599,
        0,
        0.2,
        -18,
        0,
        1.4,
        28,
        1,
        1.722,
        28,
        2.045,
        8.836,
        2.367,
        -12.396
      ]
    },
    {
      "Target": "Parameter",
      "Id": "Param_Angle_Rotation100",
      "Segments": [
        0,
        0,
        0,
        1.2,
        6,
        1,
        1.589,
        6,
        1.978,
        0.329,
        2.367,
        0.014
      ]
    },
    {
      "Target": "Parameter",
      "Id": "Param_Angle_Rotation101",
      "Segments": [
        0,
        0.31,
        0,
        0.133,
        0,
        0,
        1.333,
        9,
        1,
        1.678,
        9,
        2.022,
        5.059,
        2.367,
        0.73
      ]
    },
    {
      "Target": "Parameter",
      "Id": "Param_Angle_Rotation102",
      "Segments": [
        0,
        2.009,
        0,
        0.367,
        0,
        0,
        1.567,
        9,
        1,
        1.834,
        9,
        2.1,
        6.243,
        2.367,
        2.484
      ]
    },
    {
      "Target": "Parameter",
      "Id": "Param4",
      "Segments": [
        0,
        0,
        0,
        0.733,
        24,
        0,
        1.9,
        -13,
        1,
        2.056,
        -13,
        2.211,
        -1.676,
        2.367,
        -0.166
      ]
    },
    {
      "Target": "Parameter",
      "Id": "Param3",
      "Segments": [
        0,
        0,
        0,
        0.733,
        -9,
        0,
        1.9,
        5,
        1,
        2.056,
        5,
        2.211,
        0.644,
        2.367,
        0.064
      ]
    },
    {
      "Target": "Parameter",
      "Id": "Param_Angle_Rotation_1_houfazuochai1",
      "Segments": [
        0,
        0.312,
        1,
        0.1,
        0.125,
        0.2,
        0,
        0.3,
        0,
        0,
        1.5,
        2,
        1,
        1.789,
        2,
        2.078,
        0.957,
        2.367,
        0.377
      ]
    },
    {
      "Target": "Parameter",
      "Id": "Param_Angle_Rotation_2_houfazuochai1",
      "Segments": [
        0,
        -0.312,
        1,
        0.1,
        -0.125,
        0.2,
        0,
        0.3,
        0,
        0,
        1.5,
        -2,
        1,
        1.789,
        -2,
        2.078,
        -0.957,
        2.367,
        -0.377
      ]
    },
    {
      "Target": "Parameter",
      "Id": "Param_Angle_Rotation_3_houfazuochai1",
      "Segments": [
        0,
        -0.811,
        1,
        0.122,
        -0.335,
        0.245,
        0,
        0.367,
        0,
        0,
        1.567,
        -4,
        1,
        1.834,
        -4,
        2.1,
        -2.222,
        2.367,
        -1.037
      ]
    },
    {
      "Target": "Parameter",
      "Id": "Param_Angle_Rotation_4_houfazuochai1",
      "Segments": [
        0,
        -1.014,
        1,
        0.122,
        -0.419,
        0.245,
        0,
        0.367,
        0,
        0,
        1.567,
        -5,
        1,
        1.834,
        -5,
        2.1,
        -2.778,
        2.367,
        -1.296
      ]
    },
    {
      "Target": "Parameter",
      "Id": "Param_Angle_Rotation_5_houfazuochai1",
      "Segments": [
        0,
        -10,
        0,
        1.2,
        -4,
        1,
        1.589,
        -4,
        1.978,
        -9.671,
        2.367,
        -9.986
      ]
    },
    {
      "Target": "Parameter",
      "Id": "Param_Angle_Rotation_6_houfazuochai1",
      "Segments": [
        0,
        -14,
        0,
        1.2,
        -4,
        1,
        1.589,
        -4,
        1.978,
        -13.452,
        2.367,
        -13.977
      ]
    },
    {
      "Target": "Parameter",
      "Id": "Param_Angle_Rotation_7_houfazuochai1",
      "Segments": [
        0,
        -12,
        0,
        1.2,
        3,
        1,
        1.589,
        3,
        1.978,
        -11.178,
        2.367,
        -11.966
      ]
    },
    {
      "Target": "Parameter",
      "Id": "Param_Angle_Rotation_8_houfazuochai1",
      "Segments": [
        0,
        -11,
        0,
        1.2,
        5,
        1,
        1.589,
        5,
        1.978,
        -10.123,
        2.367,
        -10.964
      ]
    },
    {
      "Target": "Parameter",
      "Id": "Param_Angle_Rotation_9_houfazuochai1",
      "Segments": [
        0,
        -8,
        0,
        1.2,
        9,
        1,
        1.589,
        9,
        1.978,
        -7.069,
        2.367,
        -7.961
      ]
    },
    {
      "Target": "Parameter",
      "Id": "Param_Angle_Rotation_10_houfazuochai1",
      "Segments": [
        0,
        -11,
        0,
        1.2,
        12,
        1,
        1.589,
        12,
        1.978,
        -9.74,
        2.367,
        -10.948
      ]
    },
    {
      "Target": "Parameter",
      "Id": "Param_Angle_Rotation_11_houfazuochai1",
      "Segments": [
        0,
        -23,
        0,
        1.2,
        12,
        1,
        1.589,
        12,
        1.978,
        -21.083,
        2.367,
        -22.92
      ]
    },
    {
      "Target": "Parameter",
      "Id": "Param_Angle_Rotation_1_houfazuochai2",
      "Segments": [
        0,
        -0.197,
        1,
        0.078,
        -0.076,
        0.155,
        0,
        0.233,
        0,
        0,
        1.433,
        -2,
        1,
        1.744,
        -2,
        2.056,
        -0.79,
        2.367,
        -0.252
      ]
    },
    {
      "Target": "Parameter",
      "Id": "Param_Angle_Rotation_2_houfazuochai2",
      "Segments": [
        0,
        -0.197,
        1,
        0.078,
        -0.076,
        0.155,
        0,
        0.233,
        0,
        0,
        1.433,
        -2,
        1,
        1.744,
        -2,
        2.056,
        -0.79,
        2.367,
        -0.252
      ]
    },
    {
      "Target": "Parameter",
      "Id": "Param_Angle_Rotation_3_houfazuochai2",
      "Segments": [
        0,
        -0.296,
        1,
        0.078,
        -0.113,
        0.155,
        0,
        0.233,
        0,
        0,
        1.433,
        -3,
        1,
        1.744,
        -3,
        2.056,
        -1.185,
        2.367,
        -0.379
      ]
    },
    {
      "Target": "Parameter",
      "Id": "Param_Angle_Rotation_4_houfazuochai2",
      "Segments": [
        0,
        -0.567,
        1,
        0.1,
        -0.224,
        0.2,
        0,
        0.3,
        0,
        0,
        1.5,
        -4,
        1,
        1.789,
        -4,
        2.078,
        -1.914,
        2.367,
        -0.754
      ]
    },
    {
      "Target": "Parameter",
      "Id": "Param_Angle_Rotation_5_houfazuochai2",
      "Segments": [
        0,
        -0.709,
        1,
        0.1,
        -0.28,
        0.2,
        0,
        0.3,
        0,
        0,
        1.5,
        -5,
        1,
        1.789,
        -5,
        2.078,
        -2.392,
        2.367,
        -0.943
      ]
    },
    {
      "Target": "Parameter",
      "Id": "Param_Angle_Rotation_6_houfazuochai2",
      "Segments": [
        0,
        -0.85,
        1,
        0.1,
        -0.337,
        0.2,
        0,
        0.3,
        0,
        0,
        1.5,
        -6,
        1,
        1.789,
        -6,
        2.078,
        -2.87,
        2.367,
        -1.132
      ]
    },
    {
      "Target": "Parameter",
      "Id": "Param_Angle_Rotation_7_houfazuochai2",
      "Segments": [
        0,
        1.112,
        1,
        0.122,
        0.454,
        0.245,
        0,
        0.367,
        0,
        0,
        1.567,
        6,
        1,
        1.834,
        6,
        2.1,
        3.333,
        2.367,
        1.556
      ]
    },
    {
      "Target": "Parameter",
      "Id": "Param_Angle_Rotation_8_houfazuochai2",
      "Segments": [
        0,
        2.965,
        1,
        0.122,
        1.21,
        0.245,
        0,
        0.367,
        0,
        0,
        1.567,
        16,
        1,
        1.834,
        16,
        2.1,
        8.889,
        2.367,
        4.148
      ]
    },
    {
      "Target": "Parameter",
      "Id": "Param_Angle_Rotation_9_houfazuochai2",
      "Segments": [
        0,
        2.965,
        1,
        0.122,
        1.21,
        0.245,
        0,
        0.367,
        0,
        0,
        1.567,
        16,
        1,
        1.834,
        16,
        2.1,
        8.889,
        2.367,
        4.148
      ]
    },
    {
      "Target": "Parameter",
      "Id": "Param_Angle_Rotation_10_houfazuochai2",
      "Segments": [
        0,
        4.79,
        1,
        0.144,
        2.012,
        0.289,
        0,
        0.433,
        0,
        0,
        1.633,
        21,
        1,
        1.878,
        21,
        2.122,
        13.157,
        2.367,
        7.058
      ]
    },
    {
      "Target": "Parameter",
      "Id": "Param_Angle_Rotation_11_houfazuochai2",
      "Segments": [
        0,
        -0.228,
        1,
        0.144,
        -0.096,
        0.289,
        0,
        0.433,
        0,
        0,
        1.633,
        -1,
        1,
        1.878,
        -1,
        2.122,
        -0.627,
        2.367,
        -0.336
      ]
    },
    {
      "Target": "Parameter",
      "Id": "Param_Angle_Rotation_1_houfazuochai3",
      "Segments": [
        0,
        -0.21,
        1,
        0.056,
        -0.077,
        0.111,
        0,
        0.167,
        0,
        0,
        1.367,
        -4,
        1,
        1.7,
        -4,
        2.034,
        -1.222,
        2.367,
        -0.296
      ]
    },
    {
      "Target": "Parameter",
      "Id": "Param_Angle_Rotation_2_houfazuochai3",
      "Segments": [
        0,
        -0.158,
        1,
        0.056,
        -0.058,
        0.111,
        0,
        0.167,
        0,
        0,
        1.367,
        -3,
        1,
        1.7,
        -3,
        2.034,
        -0.917,
        2.367,
        -0.222
      ]
    },
    {
      "Target": "Parameter",
      "Id": "Param_Angle_Rotation_3_houfazuochai3",
      "Segments": [
        0,
        -0.357,
        1,
        0.078,
        -0.136,
        0.155,
        0,
        0.233,
        0,
        0,
        1.433,
        -4,
        1,
        1.744,
        -4,
        2.056,
        -1.58,
        2.367,
        -0.505
      ]
    },
    {
      "Target": "Parameter",
      "Id": "Param_Angle_Rotation_4_houfazuochai3",
      "Segments": [
        0,
        -0.268,
        1,
        0.078,
        -0.102,
        0.155,
        0,
        0.233,
        0,
        0,
        1.433,
        -3,
        1,
        1.744,
        -3,
        2.056,
        -1.185,
        2.367,
        -0.379
      ]
    },
    {
      "Target": "Parameter",
      "Id": "Param_Angle_Rotation_5_houfazuochai3",
      "Segments": [
        0,
        13.484,
        1,
        0.1,
        13.798,
        0.2,
        14,
        0.3,
        14,
        0,
        1.5,
        10,
        1,
        1.789,
        10,
        2.078,
        12.086,
        2.367,
        13.246
      ]
    },
    {
      "Target": "Parameter",
      "Id": "Param_Angle_Rotation_6_houfazuochai3",
      "Segments": [
        0,
        2.711,
        1,
        0.1,
        1.063,
        0.2,
        0,
        0.3,
        0,
        0,
        1.5,
        21,
        1,
        1.789,
        21,
        2.078,
        10.046,
        2.367,
        3.961
      ]
    },
    {
      "Target": "Parameter",
      "Id": "Param_Angle_Rotation_7_houfazuochai3",
      "Segments": [
        0,
        2.548,
        1,
        0.122,
        1.029,
        0.245,
        0,
        0.367,
        0,
        0,
        1.567,
        15,
        1,
        1.834,
        15,
        2.1,
        8.333,
        2.367,
        3.889
      ]
    },
    {
      "Target": "Parameter",
      "Id": "Param_Angle_Rotation_1_houfazhongc1",
      "Segments": [
        0,
        0.041,
        1,
        0.044,
        0.015,
        0.089,
        0,
        0.133,
        0,
        0,
        1.333,
        1,
        1,
        1.678,
        1,
        2.022,
        0.258,
        2.367,
        0.053
      ]
    },
    {
      "Target": "Parameter",
      "Id": "Param_Angle_Rotation_2_houfazhongc1",
      "Segments": [
        0,
        0.041,
        1,
        0.044,
        0.015,
        0.089,
        0,
        0.133,
        0,
        0,
        1.333,
        1,
        1,
        1.678,
        1,
        2.022,
        0.258,
        2.367,
        0.053
      ]
    },
    {
      "Target": "Parameter",
      "Id": "Param_Angle_Rotation_3_houfazhongc1",
      "Segments": [
        0,
        8,
        1,
        0.067,
        9.303,
        0.133,
        9,
        0.2,
        9,
        0,
        1.4,
        -4,
        1,
        1.722,
        -4,
        2.045,
        4.436,
        2.367,
        7.717
      ]
    },
    {
      "Target": "Parameter",
      "Id": "Param_Angle_Rotation_4_houfazhongc1",
      "Segments": [
        0,
        -0.247,
        1,
        0.222,
        2.222,
        0.445,
        5,
        0.667,
        5,
        0,
        1.867,
        -4,
        1,
        2.034,
        -4,
        2.2,
        -2.437,
        2.367,
        -0.615
      ]
    },
    {
      "Target": "Parameter",
      "Id": "Param_Angle_Rotation_5_houfazhongc1",
      "Segments": [
        0,
        5.255,
        1,
        0.222,
        9.37,
        0.445,
        14,
        0.667,
        14,
        0,
        1.867,
        -1,
        1,
        2.034,
        -1,
        2.2,
        1.604,
        2.367,
        4.642
      ]
    },
    {
      "Target": "Parameter",
      "Id": "Param_Angle_Rotation_6_houfazhongc1",
      "Segments": [
        0,
        -4.667,
        1,
        0.267,
        -2,
        0.533,
        2,
        0.8,
        2,
        0,
        2,
        -7,
        1,
        2.122,
        -7,
        2.245,
        -6.16,
        2.367,
        -4.993
      ]
    },
    {
      "Target": "Parameter",
      "Id": "Param_Angle_Rotation_7_houfazhongc1",
      "Segments": [
        0,
        -5.556,
        1,
        0.267,
        0.667,
        0.533,
        10,
        0.8,
        10,
        0,
        2,
        -11,
        1,
        2.122,
        -11,
        2.245,
        -9.039,
        2.367,
        -6.316
      ]
    },
    {
      "Target": "Parameter",
      "Id": "Param_Angle_Rotation_8_houfazhongc1",
      "Segments": [
        0,
        -13.981,
        1,
        0.311,
        -9.679,
        0.622,
        0,
        0.933,
        0,
        0,
        2.133,
        -16,
        1,
        2.211,
        -16,
        2.289,
        -15.395,
        2.367,
        -14.42
      ]
    },
    {
      "Target": "Parameter",
      "Id": "Param_Angle_Rotation_9_houfazhongc1",
      "Segments": [
        0,
        -2.621,
        1,
        0.311,
        -1.815,
        0.622,
        0,
        0.933,
        0,
        0,
        2.133,
        -3,
        1,
        2.211,
        -3,
        2.289,
        -2.887,
        2.367,
        -2.704
      ]
    },
    {
      "Target": "Parameter",
      "Id": "Param_Angle_Rotation_10_houfazhongc1",
      "Segments": [
        0,
        -0.053,
        1,
        0.056,
        -0.019,
        0.111,
        0,
        0.167,
        0,
        0,
        1.367,
        -1,
        1,
        1.7,
        -1,
        2.034,
        -0.306,
        2.367,
        -0.074
      ]
    },
    {
      "Target": "Parameter",
      "Id": "Param_Angle_Rotation_11_houfazhongc1",
      "Segments": [
        0,
        0.368,
        1,
        0.056,
        0.135,
        0.111,
        0,
        0.167,
        0,
        0,
        1.367,
        7,
        1,
        1.7,
        7,
        2.034,
        2.139,
        2.367,
        0.519
      ]
    },
    {
      "Target": "Parameter",
      "Id": "Param_Angle_Rotation_1_houfazhongc2",
      "Segments": [
        0,
        0.053,
        1,
        0.022,
        0.018,
        0.045,
        0,
        0.067,
        0,
        0,
        1.267,
        5,
        1,
        1.634,
        5,
        2,
        0.799,
        2.367,
        0.098
      ]
    },
    {
      "Target": "Parameter",
      "Id": "Param_Angle_Rotation_2_houfazhongc2",
      "Segments": [
        0,
        -0.011,
        1,
        0.022,
        -0.004,
        0.045,
        0,
        0.067,
        0,
        0,
        1.267,
        -1,
        1,
        1.634,
        -1,
        2,
        -0.16,
        2.367,
        -0.02
      ]
    },
    {
      "Target": "Parameter",
      "Id": "Param_Angle_Rotation_3_houfazhongc2",
      "Segments": [
        0,
        2.819,
        1,
        0.044,
        2.935,
        0.089,
        3,
        0.133,
        3,
        0,
        1.333,
        -2,
        1,
        1.678,
        -2,
        2.022,
        1.708,
        2.367,
        2.737
      ]
    },
    {
      "Target": "Parameter",
      "Id": "Param_Angle_Rotation_4_houfazhongc2",
      "Segments": [
        0,
        5.139,
        1,
        0.144,
        7.305,
        0.289,
        9,
        0.433,
        9,
        0,
        1.633,
        -4,
        1,
        1.878,
        -4,
        2.122,
        0.855,
        2.367,
        4.631
      ]
    },
    {
      "Target": "Parameter",
      "Id": "Param_Angle_Rotation_5_houfazhongc2",
      "Segments": [
        0,
        2.03,
        1,
        0.144,
        3.696,
        0.289,
        5,
        0.433,
        5,
        0,
        1.633,
        -5,
        1,
        1.878,
        -5,
        2.122,
        -1.265,
        2.367,
        1.639
      ]
    },
    {
      "Target": "Parameter",
      "Id": "Param_Angle_Rotation_6_houfazhongc2",
      "Segments": [
        0,
        0.266,
        1,
        0.233,
        4.236,
        0.467,
        9,
        0.7,
        9,
        0,
        1.9,
        -5,
        1,
        2.056,
        -5,
        2.211,
        -2.883,
        2.367,
        -0.295
      ]
    },
    {
      "Target": "Parameter",
      "Id": "Param_Angle_Rotation_7_houfazhongc2",
      "Segments": [
        0,
        9.243,
        1,
        0.178,
        13.852,
        0.355,
        18,
        0.533,
        18,
        0,
        1.7,
        -3,
        1,
        1.922,
        -3,
        2.145,
        3.481,
        2.367,
        9.243
      ]
    },
    {
      "Target": "Parameter",
      "Id": "Param_Angle_Rotation_8_houfazhongc2",
      "Segments": [
        0,
        -22,
        0,
        1.2,
        -3,
        1,
        1.589,
        -3,
        1.978,
        -20.959,
        2.367,
        -21.957
      ]
    },
    {
      "Target": "Parameter",
      "Id": "Param_Angle_Rotation_9_houfazhongc2",
      "Segments": [
        0,
        -19.731,
        1,
        0.033,
        -19.905,
        0.067,
        -20,
        0.1,
        -20,
        0,
        1.3,
        -4,
        1,
        1.656,
        -4,
        2.011,
        -16.642,
        2.367,
        -19.451
      ]
    },
    {
      "Target": "Parameter",
      "Id": "Param_Angle_Rotation_10_houfazhongc2",
      "Segments": [
        0,
        2.248,
        1,
        0.256,
        -2.469,
        0.511,
        -9,
        0.767,
        -9,
        0,
        1.967,
        7,
        1,
        2.1,
        7,
        2.234,
        5.222,
        2.367,
        2.852
      ]
    },
    {
      "Target": "Parameter",
      "Id": "Param_Angle_Rotation_11_houfazhongc2",
      "Segments": [
        0,
        25.564,
        1,
        0.256,
        29.102,
        0.511,
        34,
        0.767,
        34,
        0,
        1.967,
        22,
        1,
        2.1,
        22,
        2.234,
        23.333,
        2.367,
        25.111
      ]
    },
    {
      "Target": "Parameter",
      "Id": "Param_Angle_Rotation_1_houfazhongc3",
      "Segments": [
        0,
        0,
        0,
        1.2,
        10,
        1,
        1.589,
        10,
        1.978,
        0.548,
        2.367,
        0.023
      ]
    },
    {
      "Target": "Parameter",
      "Id": "Param_Angle_Rotation_2_houfazhongc3",
      "Segments": [
        0,
        0,
        0,
        1.2,
        -3,
        1,
        1.589,
        -3,
        1.978,
        -0.164,
        2.367,
        -0.007
      ]
    },
    {
      "Target": "Parameter",
      "Id": "Param_Angle_Rotation_3_houfazhongc3",
      "Segments": [
        0,
        1.902,
        1,
        0.033,
        1.965,
        0.067,
        2,
        0.1,
        2,
        0,
        1.3,
        -3,
        1,
        1.656,
        -3,
        2.011,
        0.951,
        2.367,
        1.829
      ]
    },
    {
      "Target": "Parameter",
      "Id": "Param_Angle_Rotation_4_houfazhongc3",
      "Segments": [
        0,
        3.862,
        1,
        0.033,
        3.951,
        0.067,
        4,
        0.1,
        4,
        0,
        1.3,
        -3,
        1,
        1.656,
        -3,
        2.011,
        2.531,
        2.367,
        3.76
      ]
    },
    {
      "Target": "Parameter",
      "Id": "Param_Angle_Rotation_5_houfazhongc3",
      "Segments": [
        0,
        3.745,
        1,
        0.067,
        3.905,
        0.133,
        4,
        0.2,
        4,
        0,
        1.4,
        0,
        1,
        1.722,
        0,
        2.045,
        2.596,
        2.367,
        3.605
      ]
    },
    {
      "Target": "Parameter",
      "Id": "Param_Angle_Rotation_6_houfazhongc3",
      "Segments": [
        0,
        3.618,
        1,
        0.067,
        3.858,
        0.133,
        4,
        0.2,
        4,
        0,
        1.4,
        -2,
        1,
        1.722,
        -2,
        2.045,
        1.894,
        2.367,
        3.408
      ]
    },
    {
      "Target": "Parameter",
      "Id": "Param_Angle_Rotation_7_houfazhongc3",
      "Segments": [
        0,
        -1.495,
        1,
        0.233,
        -0.361,
        0.467,
        1,
        0.7,
        1,
        0,
        1.9,
        -3,
        1,
        2.056,
        -3,
        2.211,
        -2.395,
        2.367,
        -1.656
      ]
    },
    {
      "Target": "Parameter",
      "Id": "Param_Angle_Rotation_8_houfazhongc3",
      "Segments": [
        0,
        -5.358,
        1,
        0.233,
        -1.104,
        0.467,
        4,
        0.7,
        4,
        0,
        1.9,
        -11,
        1,
        2.056,
        -11,
        2.211,
        -8.731,
        2.367,
        -5.959
      ]
    },
    {
      "Target": "Parameter",
      "Id": "Param_Angle_Rotation_9_houfazhongc3",
      "Segments": [
        0,
        1.444,
        1,
        0.133,
        6.333,
        0.267,
        10,
        0.4,
        10,
        0,
        1.6,
        -23,
        1,
        1.856,
        -23,
        2.111,
        -9.53,
        2.367,
        0.198
      ]
    },
    {
      "Target": "Parameter",
      "Id": "Param_Angle_Rotation_10_houfazhongc3",
      "Segments": [
        0,
        10.333,
        1,
        0.133,
        13,
        0.267,
        15,
        0.4,
        15,
        0,
        1.6,
        -3,
        1,
        1.856,
        -3,
        2.111,
        4.347,
        2.367,
        9.654
      ]
    },
    {
      "Target": "Parameter",
      "Id": "Param_Angle_Rotation_11_houfazhongc3",
      "Segments": [
        0,
        9.852,
        1,
        0.133,
        16.222,
        0.267,
        21,
        0.4,
        21,
        0,
        1.6,
        -22,
        1,
        1.856,
        -22,
        2.111,
        -4.448,
        2.367,
        8.228
      ]
    },
    {
      "Target": "Parameter",
      "Id": "Param_Angle_Rotation_2_houfazhongc4",
      "Segments": [
        0,
        -0.039,
        1,
        0.367,
        -0.319,
        0.733,
        -2,
        1.1,
        -2,
        0,
        2.3,
        0,
        1,
        2.322,
        0,
        2.345,
        -0.006,
        2.367,
        -0.018
      ]
    },
    {
      "Target": "Parameter",
      "Id": "Param_Angle_Rotation_3_houfazhongc4",
      "Segments": [
        0,
        1.995,
        1,
        0.011,
        1.998,
        0.022,
        2,
        0.033,
        2,
        0,
        1.233,
        0,
        1,
        1.611,
        0,
        1.989,
        1.784,
        2.367,
        1.982
      ]
    },
    {
      "Target": "Parameter",
      "Id": "Param_Angle_Rotation_4_houfazhongc4",
      "Segments": [
        0,
        5.989,
        1,
        0.011,
        5.996,
        0.022,
        6,
        0.033,
        6,
        0,
        1.233,
        2,
        1,
        1.611,
        2,
        1.989,
        5.568,
        2.367,
        5.964
      ]
    },
    {
      "Target": "Parameter",
      "Id": "Param_Angle_Rotation_5_houfazhongc4",
      "Segments": [
        0,
        5.05,
        1,
        0.056,
        5.018,
        0.111,
        5,
        0.167,
        5,
        0,
        1.367,
        6,
        1,
        1.7,
        6,
        2.034,
        5.306,
        2.367,
        5.074
      ]
    },
    {
      "Target": "Parameter",
      "Id": "Param_Angle_Rotation_6_houfazhongc4",
      "Segments": [
        0,
        2.651,
        1,
        0.056,
        2.872,
        0.111,
        3,
        0.167,
        3,
        0,
        1.367,
        -4,
        1,
        1.7,
        -4,
        2.034,
        0.861,
        2.367,
        2.481
      ]
    },
    {
      "Target": "Parameter",
      "Id": "Param_Angle_Rotation_7_houfazhongc4",
      "Segments": [
        0,
        -1.481,
        1,
        0.1,
        -0.578,
        0.2,
        0,
        0.3,
        0,
        0,
        1.5,
        -12,
        1,
        1.789,
        -12,
        2.078,
        -5.741,
        2.367,
        -2.263
      ]
    },
    {
      "Target": "Parameter",
      "Id": "Param_Angle_Rotation_8_houfazhongc4",
      "Segments": [
        0,
        -0.494,
        1,
        0.1,
        -0.193,
        0.2,
        0,
        0.3,
        0,
        0,
        1.5,
        -4,
        1,
        1.789,
        -4,
        2.078,
        -1.914,
        2.367,
        -0.754
      ]
    },
    {
      "Target": "Parameter",
      "Id": "Param_Angle_Rotation_9_houfazhongc4",
      "Segments": [
        0,
        -1.213,
        1,
        0.144,
        -0.501,
        0.289,
        0,
        0.433,
        0,
        0,
        1.633,
        -6,
        1,
        1.878,
        -6,
        2.122,
        -3.759,
        2.367,
        -2.016
      ]
    },
    {
      "Target": "Parameter",
      "Id": "Param_Angle_Rotation_10_houfazhongc4",
      "Segments": [
        0,
        -1.011,
        1,
        0.144,
        -0.417,
        0.289,
        0,
        0.433,
        0,
        0,
        1.633,
        -5,
        1,
        1.878,
        -5,
        2.122,
        -3.133,
        2.367,
        -1.68
      ]
    },
    {
      "Target": "Parameter",
      "Id": "Param_Angle_Rotation_11_houfazhongc4",
      "Segments": [
        0,
        -0.809,
        1,
        0.144,
        -0.334,
        0.289,
        0,
        0.433,
        0,
        0,
        1.633,
        -4,
        1,
        1.878,
        -4,
        2.122,
        -2.506,
        2.367,
        -1.344
      ]
    },
    {
      "Target": "Parameter",
      "Id": "Param_Angle_Rotation_12_houfazhongc4",
      "Segments": [
        0,
        -0.606,
        1,
        0.144,
        -0.25,
        0.289,
        0,
        0.433,
        0,
        0,
        1.633,
        -3,
        1,
        1.878,
        -3,
        2.122,
        -1.88,
        2.367,
        -1.008
      ]
    },
    {
      "Target": "Parameter",
      "Id": "Param_Angle_Rotation_1_houfazhongc5",
      "Segments": [
        0,
        -0.955,
        1,
        0.178,
        -0.47,
        0.355,
        0,
        0.533,
        0,
        0,
        1.733,
        -2,
        1,
        1.944,
        -2,
        2.156,
        -1.443,
        2.367,
        -0.917
      ]
    },
    {
      "Target": "Parameter",
      "Id": "Param_Angle_Rotation_2_houfazhongc5",
      "Segments": [
        0,
        -1.432,
        1,
        0.178,
        -0.705,
        0.355,
        0,
        0.533,
        0,
        0,
        1.733,
        -3,
        1,
        1.944,
        -3,
        2.156,
        -2.164,
        2.367,
        -1.375
      ]
    },
    {
      "Target": "Parameter",
      "Id": "Param_Angle_Rotation_3_houfazhongc5",
      "Segments": [
        0,
        -0.955,
        1,
        0.178,
        -0.47,
        0.355,
        0,
        0.533,
        0,
        0,
        1.733,
        -2,
        1,
        1.944,
        -2,
        2.156,
        -1.443,
        2.367,
        -0.917
      ]
    },
    {
      "Target": "Parameter",
      "Id": "Param_Angle_Rotation_4_houfazhongc5",
      "Segments": [
        0,
        -1.043,
        1,
        0.2,
        -0.529,
        0.4,
        0,
        0.6,
        0,
        0,
        1.8,
        -2,
        1,
        1.989,
        -2,
        2.178,
        -1.554,
        2.367,
        -1.083
      ]
    },
    {
      "Target": "Parameter",
      "Id": "Param_Angle_Rotation_5_houfazhongc5",
      "Segments": [
        0,
        -2.607,
        1,
        0.2,
        -1.322,
        0.4,
        0,
        0.6,
        0,
        0,
        1.8,
        -5,
        1,
        1.989,
        -5,
        2.178,
        -3.885,
        2.367,
        -2.708
      ]
    },
    {
      "Target": "Parameter",
      "Id": "Param_Angle_Rotation_6_houfazhongc5",
      "Segments": [
        0,
        -2.803,
        1,
        0.222,
        -1.461,
        0.445,
        0,
        0.667,
        0,
        0,
        1.867,
        -5,
        1,
        2.034,
        -5,
        2.2,
        -4.132,
        2.367,
        -3.119
      ]
    },
    {
      "Target": "Parameter",
      "Id": "Param_Angle_Rotation_7_houfazhongc5",
      "Segments": [
        0,
        -7,
        0,
        1.2,
        4,
        1,
        1.589,
        4,
        1.978,
        -6.397,
        2.367,
        -6.975
      ]
    },
    {
      "Target": "Parameter",
      "Id": "Param_Angle_Rotation_8_houfazhongc5",
      "Segments": [
        0,
        -10,
        0,
        1.2,
        8,
        1,
        1.589,
        8,
        1.978,
        -9.014,
        2.367,
        -9.959
      ]
    },
    {
      "Target": "Parameter",
      "Id": "Param_Angle_Rotation_9_houfazhongc5",
      "Segments": [
        0,
        -11,
        0,
        1.2,
        16,
        1,
        1.589,
        16,
        1.978,
        -9.521,
        2.367,
        -10.939
      ]
    },
    {
      "Target": "Parameter",
      "Id": "Param_Angle_Rotation_10_houfazhongc5",
      "Segments": [
        0,
        -10,
        0,
        1.2,
        21,
        1,
        1.589,
        21,
        1.978,
        -8.302,
        2.367,
        -9.93
      ]
    },
    {
      "Target": "Parameter",
      "Id": "Param_Angle_Rotation_1_houfazhongc6",
      "Segments": [
        0,
        -0.343,
        1,
        0.144,
        -0.155,
        0.289,
        0,
        0.433,
        0,
        0,
        1.633,
        -1,
        1,
        1.878,
        -1,
        2.122,
        -0.627,
        2.367,
        -0.336
      ]
    },
    {
      "Target": "Parameter",
      "Id": "Param_Angle_Rotation_2_houfazhongc6",
      "Segments": [
        0,
        -0.687,
        1,
        0.144,
        -0.31,
        0.289,
        0,
        0.433,
        0,
        0,
        1.633,
        -2,
        1,
        1.878,
        -2,
        2.122,
        -1.253,
        2.367,
        -0.672
      ]
    },
    {
      "Target": "Parameter",
      "Id": "Param_Angle_Rotation_3_houfazhongc6",
      "Segments": [
        0,
        -1.03,
        1,
        0.144,
        -0.466,
        0.289,
        0,
        0.433,
        0,
        0,
        1.633,
        -3,
        1,
        1.878,
        -3,
        2.122,
        -1.88,
        2.367,
        -1.008
      ]
    },
    {
      "Target": "Parameter",
      "Id": "Param_Angle_Rotation_4_houfazhongc6",
      "Segments": [
        0,
        -1.03,
        1,
        0.144,
        -0.466,
        0.289,
        0,
        0.433,
        0,
        0,
        1.633,
        -3,
        1,
        1.878,
        -3,
        2.122,
        -1.88,
        2.367,
        -1.008
      ]
    },
    {
      "Target": "Parameter",
      "Id": "Param_Angle_Rotation_5_houfazhongc6",
      "Segments": [
        0,
        -1.968,
        1,
        0.167,
        -0.918,
        0.333,
        0,
        0.5,
        0,
        0,
        1.7,
        -5,
        1,
        1.922,
        -5,
        2.145,
        -3.457,
        2.367,
        -2.085
      ]
    },
    {
      "Target": "Parameter",
      "Id": "Param_Angle_Rotation_6_houfazhongc6",
      "Segments": [
        0,
        -3,
        0,
        1.2,
        -2,
        1,
        1.589,
        -2,
        1.978,
        -2.945,
        2.367,
        -2.998
      ]
    },
    {
      "Target": "Parameter",
      "Id": "Param_Angle_Rotation_7_houfazhongc6",
      "Segments": [
        0,
        -8,
        0,
        1.2,
        -3,
        1,
        1.589,
        -3,
        1.978,
        -7.726,
        2.367,
        -7.989
      ]
    },
    {
      "Target": "Parameter",
      "Id": "Param_Angle_Rotation_8_houfazhongc6",
      "Segments": [
        0,
        -10,
        0,
        1.2,
        1,
        1,
        1.589,
        1,
        1.978,
        -9.397,
        2.367,
        -9.975
      ]
    },
    {
      "Target": "Parameter",
      "Id": "Param_Angle_Rotation_9_houfazhongc6",
      "Segments": [
        0,
        -34,
        0,
        1.2,
        12,
        1,
        1.589,
        12,
        1.978,
        -31.48,
        2.367,
        -33.895
      ]
    },
    {
      "Target": "Parameter",
      "Id": "Param_Angle_Rotation_10_houfazhongc6",
      "Segments": [
        0,
        -11,
        0,
        1.2,
        16,
        1,
        1.589,
        16,
        1.978,
        -9.521,
        2.367,
        -10.939
      ]
    },
    {
      "Target": "Parameter",
      "Id": "Param_Angle_Rotation_1_houfazhongc7",
      "Segments": [
        0,
        -2.858,
        1,
        0.111,
        -1.194,
        0.222,
        0,
        0.333,
        0,
        0,
        1.533,
        -13,
        1,
        1.811,
        -13,
        2.089,
        -6.731,
        2.367,
        -2.899
      ]
    },
    {
      "Target": "Parameter",
      "Id": "Param_Angle_Rotation_2_houfazhongc7",
      "Segments": [
        0,
        -1.539,
        1,
        0.111,
        -0.643,
        0.222,
        0,
        0.333,
        0,
        0,
        1.533,
        -7,
        1,
        1.811,
        -7,
        2.089,
        -3.624,
        2.367,
        -1.561
      ]
    },
    {
      "Target": "Parameter",
      "Id": "Param_Angle_Rotation_3_houfazhongc7",
      "Segments": [
        0,
        -1.319,
        1,
        0.111,
        -0.551,
        0.222,
        0,
        0.333,
        0,
        0,
        1.533,
        -6,
        1,
        1.811,
        -6,
        2.089,
        -3.106,
        2.367,
        -1.338
      ]
    },
    {
      "Target": "Parameter",
      "Id": "Param_Angle_Rotation_4_houfazhongc7",
      "Segments": [
        0,
        0,
        2,
        0.4,
        0,
        0,
        1.2,
        11,
        0,
        1.6,
        0,
        2,
        2.367,
        0
      ]
    },
    {
      "Target": "Parameter",
      "Id": "Param_Angle_Rotation_5_houfazhongc7",
      "Segments": [
        0,
        -2,
        0,
        1.2,
        3,
        1,
        1.589,
        3,
        1.978,
        -1.726,
        2.367,
        -1.989
      ]
    },
    {
      "Target": "Parameter",
      "Id": "Param_Angle_Rotation_6_houfazhongc7",
      "Segments": [
        0,
        -7,
        0,
        1.2,
        3,
        1,
        1.589,
        3,
        1.978,
        -6.452,
        2.367,
        -6.977
      ]
    },
    {
      "Target": "Parameter",
      "Id": "Param_Angle_Rotation_7_houfazhongc7",
      "Segments": [
        0,
        -9,
        0,
        1.2,
        5,
        1,
        1.589,
        5,
        1.978,
        -8.233,
        2.367,
        -8.968
      ]
    },
    {
      "Target": "Parameter",
      "Id": "Param_Angle_Rotation_8_houfazhongc7",
      "Segments": [
        0,
        -11,
        0,
        1.2,
        4,
        1,
        1.589,
        4,
        1.978,
        -10.178,
        2.367,
        -10.966
      ]
    },
    {
      "Target": "Parameter",
      "Id": "Param_Angle_Rotation_9_houfazhongc7",
      "Segments": [
        0,
        -10,
        0,
        1.2,
        1,
        1,
        1.589,
        1,
        1.978,
        -9.397,
        2.367,
        -9.975
      ]
    },
    {
      "Target": "Parameter",
      "Id": "Param_Angle_Rotation_10_houfazhongc7",
      "Segments": [
        0,
        -8,
        0,
        1.2,
        12,
        1,
        1.589,
        12,
        1.978,
        -6.904,
        2.367,
        -7.955
      ]
    },
    {
      "Target": "Parameter",
      "Id": "Param_Angle_Rotation_11_houfazhongc7",
      "Segments": [
        0,
        -10,
        0,
        1.2,
        12,
        1,
        1.589,
        12,
        1.978,
        -8.795,
        2.367,
        -9.95
      ]
    },
    {
      "Target": "Parameter",
      "Id": "Param_Angle_Rotation_12_houfazhongc7",
      "Segments": [
        0,
        -15,
        0,
        1.2,
        17,
        1,
        1.589,
        17,
        1.978,
        -13.247,
        2.367,
        -14.927
      ]
    },
    {
      "Target": "Parameter",
      "Id": "Param_Angle_Rotation_13_houfazhongc7",
      "Segments": [
        0,
        -11,
        0,
        1.2,
        15,
        1,
        1.589,
        15,
        1.978,
        -9.576,
        2.367,
        -10.941
      ]
    },
    {
      "Target": "Parameter",
      "Id": "Param_Angle_Rotation_2_houfazhongc8",
      "Segments": [
        0,
        -4.421,
        1,
        0.078,
        -4.775,
        0.155,
        -5,
        0.233,
        -5,
        0,
        1.433,
        0,
        1,
        1.744,
        0,
        2.056,
        -3.025,
        2.367,
        -4.369
      ]
    },
    {
      "Target": "Parameter",
      "Id": "Param_Angle_Rotation_3_houfazhongc8",
      "Segments": [
        0,
        -7.073,
        1,
        0.078,
        -7.64,
        0.155,
        -8,
        0.233,
        -8,
        0,
        1.433,
        0,
        1,
        1.744,
        0,
        2.056,
        -4.84,
        2.367,
        -6.99
      ]
    },
    {
      "Target": "Parameter",
      "Id": "Param_Angle_Rotation_4_houfazhongc8",
      "Segments": [
        0,
        0.884,
        1,
        0.078,
        0.955,
        0.155,
        1,
        0.233,
        1,
        0,
        1.433,
        0,
        1,
        1.744,
        0,
        2.056,
        0.605,
        2.367,
        0.874
      ]
    },
    {
      "Target": "Parameter",
      "Id": "Param_Angle_Rotation_5_houfazhongc8",
      "Segments": [
        0,
        -6.189,
        1,
        0.078,
        -6.685,
        0.155,
        -7,
        0.233,
        -7,
        0,
        1.433,
        0,
        1,
        1.744,
        0,
        2.056,
        -4.235,
        2.367,
        -6.117
      ]
    },
    {
      "Target": "Parameter",
      "Id": "Param_Angle_Rotation_6_houfazhongc8",
      "Segments": [
        0,
        10.609,
        1,
        0.078,
        11.46,
        0.155,
        12,
        0.233,
        12,
        0,
        1.433,
        0,
        1,
        1.744,
        0,
        2.056,
        7.259,
        2.367,
        10.486
      ]
    },
    {
      "Target": "Parameter",
      "Id": "Param_Angle_Rotation_7_houfazhongc8",
      "Segments": [
        0,
        -3.536,
        1,
        0.078,
        -3.82,
        0.155,
        -4,
        0.233,
        -4,
        0,
        1.433,
        0,
        1,
        1.744,
        0,
        2.056,
        -2.42,
        2.367,
        -3.495
      ]
    },
    {
      "Target": "Parameter",
      "Id": "Param_Angle_Rotation_8_houfazhongc8",
      "Segments": [
        0,
        -6.189,
        1,
        0.078,
        -6.685,
        0.155,
        -7,
        0.233,
        -7,
        0,
        1.433,
        0,
        1,
        1.744,
        0,
        2.056,
        -4.235,
        2.367,
        -6.117
      ]
    },
    {
      "Target": "Parameter",
      "Id": "Param_Angle_Rotation_9_houfazhongc8",
      "Segments": [
        0,
        -12.377,
        1,
        0.078,
        -13.37,
        0.155,
        -14,
        0.233,
        -14,
        0,
        1.433,
        0,
        1,
        1.744,
        0,
        2.056,
        -8.469,
        2.367,
        -12.233
      ]
    },
    {
      "Target": "Parameter",
      "Id": "Param_Angle_Rotation_1_houfazhongc9",
      "Segments": [
        0,
        0.197,
        1,
        0.078,
        0.076,
        0.155,
        0,
        0.233,
        0,
        0,
        1.433,
        2,
        1,
        1.744,
        2,
        2.056,
        0.79,
        2.367,
        0.252
      ]
    },
    {
      "Target": "Parameter",
      "Id": "Param_Angle_Rotation_2_houfazhongc9",
      "Segments": [
        0,
        -0.099,
        1,
        0.078,
        -0.038,
        0.155,
        0,
        0.233,
        0,
        0,
        1.433,
        -1,
        1,
        1.744,
        -1,
        2.056,
        -0.395,
        2.367,
        -0.126
      ]
    },
    {
      "Target": "Parameter",
      "Id": "Param_Angle_Rotation_3_houfazhongc9",
      "Segments": [
        0,
        -2.836,
        1,
        0.111,
        -2.934,
        0.222,
        -3,
        0.333,
        -3,
        0,
        1.533,
        -2,
        1,
        1.811,
        -2,
        2.089,
        -2.482,
        2.367,
        -2.777
      ]
    },
    {
      "Target": "Parameter",
      "Id": "Param_Angle_Rotation_4_houfazhongc9",
      "Segments": [
        0,
        -5.491,
        1,
        0.111,
        -5.197,
        0.222,
        -5,
        0.333,
        -5,
        0,
        1.533,
        -8,
        1,
        1.811,
        -8,
        2.089,
        -6.553,
        2.367,
        -5.669
      ]
    },
    {
      "Target": "Parameter",
      "Id": "Param_Angle_Rotation_5_houfazhongc9",
      "Segments": [
        0,
        1.201,
        1,
        0.111,
        2.277,
        0.222,
        3,
        0.333,
        3,
        0,
        1.533,
        -8,
        1,
        1.811,
        -8,
        2.089,
        -2.695,
        2.367,
        0.547
      ]
    },
    {
      "Target": "Parameter",
      "Id": "Param_Angle_Rotation_6_houfazhongc9",
      "Segments": [
        0,
        6.365,
        1,
        0.111,
        7.343,
        0.222,
        8,
        0.333,
        8,
        0,
        1.533,
        -2,
        1,
        1.811,
        -2,
        2.089,
        2.823,
        2.367,
        5.77
      ]
    },
    {
      "Target": "Parameter",
      "Id": "Param_Angle_Rotation_7_houfazhongc9",
      "Segments": [
        0,
        9.019,
        1,
        0.111,
        9.606,
        0.222,
        10,
        0.333,
        10,
        0,
        1.533,
        4,
        1,
        1.811,
        4,
        2.089,
        6.894,
        2.367,
        8.662
      ]
    },
    {
      "Target": "Parameter",
      "Id": "Param_Angle_Rotation_8_houfazhongc9",
      "Segments": [
        0,
        10.371,
        1,
        0.122,
        10.151,
        0.245,
        10,
        0.367,
        10,
        0,
        1.567,
        12,
        1,
        1.834,
        12,
        2.1,
        11.06,
        2.367,
        10.468
      ]
    },
    {
      "Target": "Parameter",
      "Id": "Param_Angle_Rotation_9_houfazhongc9",
      "Segments": [
        0,
        8.074,
        1,
        0.122,
        8.622,
        0.245,
        9,
        0.367,
        9,
        0,
        1.567,
        4,
        1,
        1.834,
        4,
        2.1,
        6.351,
        2.367,
        7.829
      ]
    },
    {
      "Target": "Parameter",
      "Id": "Param_Angle_Rotation_10_houfazhongc9",
      "Segments": [
        0,
        11.294,
        1,
        0.122,
        13.487,
        0.245,
        15,
        0.367,
        15,
        0,
        1.567,
        -5,
        1,
        1.834,
        -5,
        2.1,
        4.404,
        2.367,
        10.315
      ]
    },
    {
      "Target": "Parameter",
      "Id": "Param_Angle_Rotation_11_houfazhongc9",
      "Segments": [
        0,
        -0.556,
        1,
        0.122,
        -0.227,
        0.245,
        0,
        0.367,
        0,
        0,
        1.567,
        -3,
        1,
        1.834,
        -3,
        2.1,
        -1.589,
        2.367,
        -0.703
      ]
    },
    {
      "Target": "Parameter",
      "Id": "Param_Angle_Rotation_12_houfazhongc9",
      "Segments": [
        0,
        -3.52,
        1,
        0.122,
        -1.437,
        0.245,
        0,
        0.367,
        0,
        0,
        1.567,
        -19,
        1,
        1.834,
        -19,
        2.1,
        -10.066,
        2.367,
        -4.451
      ]
    },
    {
      "Target": "Parameter",
      "Id": "Param_Angle_Rotation_13_houfazhongc9",
      "Segments": [
        0,
        -0.741,
        1,
        0.122,
        -0.303,
        0.245,
        0,
        0.367,
        0,
        0,
        1.567,
        -4,
        1,
        1.834,
        -4,
        2.1,
        -2.119,
        2.367,
        -0.937
      ]
    },
    {
      "Target": "Parameter",
      "Id": "ParamEyeLSmile",
      "Segments": [
        0,
        0,
        0,
        2.367,
        0
      ]
    },
    {
      "Target": "Parameter",
      "Id": "ParamEyeRSmile",
      "Segments": [
        0,
        0,
        0,
        2.367,
        0
      ]
    },
    {
      "Target": "Parameter",
      "Id": "Param53",
      "Segments": [
        0,
        0,
        0,
        2.367,
        0
      ]
    },
    {
      "Target": "Parameter",
      "Id": "Param54",
      "Segments": [
        0,
        0,
        0,
        2.367,
        0
      ]
    },
    {
      "Target": "Parameter",
      "Id": "Param55",
      "Segments": [
        0,
        0,
        0,
        2.367,
        0
      ]
    },
    {
      "Target": "Parameter",
      "Id": "Param56",
      "Segments": [
        0,
        0,
        0,
        2.367,
        0
      ]
    },
    {
      "Target": "Parameter",
      "Id": "ParamEyeBallX",
      "Segments": [
        0,
        0,
        0,
        2.367,
        0
      ]
    },
    {
      "Target": "Parameter",
      "Id": "ParamEyeBallY",
      "Segments": [
        0,
        0,
        0,
        2.367,
        0
      ]
    },
    {
      "Target": "Parameter",
      "Id": "Param47",
      "Segments": [
        0,
        -30,
        0,
        2.367,
        -30
      ]
    },
    {
      "Target": "Parameter",
      "Id": "Param51",
      "Segments": [
        0,
        -30,
        0,
        2.367,
        -30
      ]
    },
    {
      "Target": "Parameter",
      "Id": "Param48",
      "Segments": [
        0,
        -30,
        0,
        2.367,
        -30
      ]
    },
    {
      "Target": "Parameter",
      "Id": "Param52",
      "Segments": [
        0,
        -30,
        0,
        2.367,
        -30
      ]
    },
    {
      "Target": "Parameter",
      "Id": "ParamBrowLY",
      "Segments": [
        0,
        0,
        0,
        2.367,
        0
      ]
    },
    {
      "Target": "Parameter",
      "Id": "ParamBrowRY",
      "Segments": [
        0,
        0,
        0,
        2.367,
        0
      ]
    },
    {
      "Target": "Parameter",
      "Id": "ParamBrowLAngle",
      "Segments": [
        0,
        0,
        0,
        2.367,
        0
      ]
    },
    {
      "Target": "Parameter",
      "Id": "ParamBrowRAngle",
      "Segments": [
        0,
        0,
        0,
        2.367,
        0
      ]
    },
    {
      "Target": "Parameter",
      "Id": "ParamBrowLForm",
      "Segments": [
        0,
        0,
        0,
        2.367,
        0
      ]
    },
    {
      "Target": "Parameter",
      "Id": "ParamBrowRForm",
      "Segments": [
        0,
        0,
        0,
        2.367,
        0
      ]
    },
    {
      "Target": "Parameter",
      "Id": "ParamMouthForm",
      "Segments": [
        0,
        -1,
        0,
        2.367,
        -1
      ]
    },
    {
      "Target": "Parameter",
      "Id": "Param49",
      "Segments": [
        0,
        -1,
        0,
        2.367,
        -1
      ]
    },
    {
      "Target": "Parameter",
      "Id": "Param50",
      "Segments": [
        0,
        0,
        0,
        2.367,
        0
      ]
    },
    {
      "Target": "Parameter",
      "Id": "ParamMouthOpenY",
      "Segments": [
        0,
        0,
        0,
        2.367,
        0
      ]
    },
    {
      "Target": "Parameter",
      "Id": "Param2",
      "Segments": [
        0,
        0,
        0,
        2.367,
        0
      ]
    },
    {
      "Target": "Parameter",
      "Id": "Param_Angle_Rotation22",
      "Segments": [
        0,
        0,
        0,
        2.367,
        0
      ]
    },
    {
      "Target": "Parameter",
      "Id": "Param_Angle_Rotation25",
      "Segments": [
        0,
        0,
        0,
        2.367,
        0
      ]
    },
    {
      "Target": "Parameter",
      "Id": "Param_Angle_Rotation32",
      "Segments": [
        0,
        0,
        0,
        2.367,
        0
      ]
    },
    {
      "Target": "Parameter",
      "Id": "Param_Angle_Rotation_12_houfazuochai2",
      "Segments": [
        0,
        0,
        0,
        2.367,
        0
      ]
    },
    {
      "Target": "Parameter",
      "Id": "Param_Angle_Rotation_13_houfazuochai2",
      "Segments": [
        0,
        0,
        0,
        2.367,
        0
      ]
    },
    {
      "Target": "Parameter",
      "Id": "Param_Angle_Rotation_14_houfazuochai2",
      "Segments": [
        0,
        0,
        0,
        2.367,
        0
      ]
    },
    {
      "Target": "Parameter",
      "Id": "Param_Angle_Rotation_15_houfazuochai2",
      "Segments": [
        0,
        0,
        0,
        2.367,
        0
      ]
    },
    {
      "Target": "Parameter",
      "Id": "Param_Angle_Rotation_8_houfazuochai3",
      "Segments": [
        0,
        0,
        0,
        2.367,
        0
      ]
    },
    {
      "Target": "Parameter",
      "Id": "Param_Angle_Rotation_9_houfazuochai3",
      "Segments": [
        0,
        0,
        0,
        2.367,
        0
      ]
    },
    {
      "Target": "Parameter",
      "Id": "Param_Angle_Rotation_10_houfazuochai3",
      "Segments": [
        0,
        0,
        0,
        2.367,
        0
      ]
    },
    {
      "Target": "Parameter",
      "Id": "Param_Angle_Rotation_11_houfazuochai3",
      "Segments": [
        0,
        0,
        0,
        2.367,
        0
      ]
    },
    {
      "Target": "Parameter",
      "Id": "Param_Angle_Rotation_1_houfazhongc4",
      "Segments": [
        0,
        0,
        0,
        2.367,
        0
      ]
    },
    {
      "Target": "Parameter",
      "Id": "Param_Angle_Rotation_1_houfazhongc8",
      "Segments": [
        0,
        0,
        0,
        2.367,
        0
      ]
    },
    {
      "Target": "Parameter",
      "Id": "Param_Angle_Rotation_10_houfazhongc8",
      "Segments": [
        0,
        0,
        0,
        2.367,
        0
      ]
    }
  ],
  "UserData": [
    {
      "Time": 0.0,
      "Value": ""
    }
  ]
}